pinecil/__init__.py
pinecil/ble.py
pinecil/crx_uuid_name_map.py
pinecil/pinecil.py
pinecil/pinecil_setting_limits.py
pinecil-0.2.15.dist-info/LICENSE
pinecil-0.2.15.dist-info/METADATA
pinecil-0.2.15.dist-info/WHEEL
pinecil-0.2.15.dist-info/RECORD
