Metadata-Version: 2.1
Name: pinecil
Version: 0.2.15
Summary: A python interface for Pinecil V2 controls and settings.
Home-page: https://github.com/builder555/pinecil_lib
License: MIT-0
Author: builder555
Author-email: 85308587+builder555@users.noreply.github.com
Requires-Python: >=3.9,<3.13
Classifier: License :: OSI Approved
Classifier: Programming Language :: Python :: 3
Classifier: Programming Language :: Python :: 3.9
Classifier: Programming Language :: Python :: 3.10
Classifier: Programming Language :: Python :: 3.11
Classifier: Programming Language :: Python :: 3.12
Requires-Dist: bleak (>=0.21.1)
